LICENSE
MANIFEST.in
README.rst
setup.py
django_mixins.egg-info/PKG-INFO
django_mixins.egg-info/SOURCES.txt
django_mixins.egg-info/dependency_links.txt
django_mixins.egg-info/not-zip-safe
django_mixins.egg-info/top_level.txt
mixins/__init__.py
mixins/decorators.py
mixins/models.py
mixins/tests.py
mixins/views.py
mixins/compat/__init__.py
mixins/compat/urls.py