Metadata-Version: 1.1
Name: django-mixins
Version: 0.0.9
Summary: Useful mixins for Django class based views
Home-page: http://github.com/flashingpumpkin/django-mixins
Author: Alen Mujezinovic
Author-email: alen@caffeinehit.com
License: UNKNOWN
Keywords: django views mixins
Platform: UNKNOWN
Classifier: Development Status :: 4 - Beta
Classifier: Intended Audience :: Developers
Classifier: Topic :: Software Development :: Libraries :: Python Modules
Classifier: Environment :: Web Environment
Classifier: Topic :: Internet
Classifier: Operating System :: OS Independent
Classifier: Programming Language :: Python
Classifier: Framework :: Django
